src/open8_dmem.v
// Data memory (SRAM): 8-bit cells, asynchronous read, synchronous write.
module open8_dmem #(
    parameter ADDR_W   = 12,   // 4 KB
    parameter BUS_W    = 16
)(
    input  wire              clk,
    input  wire [BUS_W-1:0]  addr,
    input  wire              we,
    input  wire [7:0]        wdata,
    output wire [7:0]        rdata
);
    reg [7:0] mem [0:(1<<ADDR_W)-1];

    integer i;
    initial for (i = 0; i < (1<<ADDR_W); i = i + 1) mem[i] = 8'h00;

    wire [ADDR_W-1:0] a = addr[ADDR_W-1:0];

    always @(posedge clk) if (we) mem[a] <= wdata;

    assign rdata = mem[a];
endmodule

src/open8_pmem.v
// Program memory: 16-bit words, dual asynchronous read port.
// Initialised from a hex file (one 16-bit word per line) via $readmemh.
module open8_pmem #(
    parameter ADDR_W = 12,
    parameter INIT   = "program.hex"
)(
    input  wire [ADDR_W-1:0] addr_a,
    output wire [15:0]       data_a,
    input  wire [ADDR_W-1:0] addr_b,
    output wire [15:0]       data_b
);
    reg [15:0] mem [0:(1<<ADDR_W)-1];

    integer i;
    initial begin
        for (i = 0; i < (1<<ADDR_W); i = i + 1) mem[i] = 16'h0000;
        $readmemh(INIT, mem);
    end

    assign data_a = mem[addr_a];
    assign data_b = mem[addr_b];
endmodule

src/open8_core.v
// ============================================================================
// Open8 - the simplest soft-core implementation of the Open8 8-bit MCU
// (AVR-inspired ISA described in the project markdown spec).
//
// Design choices for simplicity:
//   * Single-cycle execution: one instruction completes every clock.
//   * Harvard architecture: separate program (16-bit word) and data (8-bit)
//     memories, both with asynchronous (combinational) read.
//   * 32 x 8-bit general purpose registers (R0..R31).
//   * 8-bit status register SREG = {I,T,H,S,V,N,Z,C}.
//   * Two-word instructions (LDS/STS) read the following program word in the
//     same cycle (async ROM), so they still complete in one clock.
//
// Implemented subset of the Open8/AVR ISA:
//   ALU   : ADD ADC SUB SBC AND OR EOR MOV CP CPC
//   IMM   : LDI SUBI ORI ANDI CPI
//   UNARY : COM NEG SWAP INC DEC ASR LSR ROR   (LSL/ROL via ADD/ADC Rd,Rd)
//   FLOW  : RJMP BREQ BRNE BRCS BRCC
//   MEM   : LDS STS
//   IO    : IN OUT
//   CTRL  : NOP SEI CLI SLEEP
// ============================================================================

module open8_core #(
    parameter PROG_ADDR_W = 12,   // program memory address width (words)
    parameter DATA_ADDR_W = 16    // data address bus width
)(
    input  wire                    clk,
    input  wire                    rst_n,

    // Program memory: dual asynchronous read (current word + next word).
    output wire [PROG_ADDR_W-1:0]  pmem_addr_a,
    input  wire [15:0]             pmem_data_a,
    output wire [PROG_ADDR_W-1:0]  pmem_addr_b,
    input  wire [15:0]             pmem_data_b,

    // Data memory: asynchronous read, synchronous write.
    output reg  [DATA_ADDR_W-1:0]  dmem_addr,
    output reg                     dmem_we,
    output reg  [7:0]              dmem_wdata,
    input  wire [7:0]              dmem_rdata,

    // Simple I/O bus (OUT writes / IN reads).
    output reg                     io_we,
    output reg  [5:0]              io_addr,
    output reg  [7:0]              io_wdata,
    input  wire [7:0]              io_rdata,

    // Status.
    output wire                    halted,

    // Debug read port (tool-independent introspection for the testbench).
    input  wire [4:0]              dbg_addr,
    output wire [7:0]              dbg_data,
    output wire [7:0]              dbg_sreg,
    output wire [15:0]             dbg_pc
);

    // ---- SREG bit positions -------------------------------------------------
    localparam C = 0, Z = 1, N = 2, V = 3, S = 4, H = 5, T = 6, I = 7;

    // ---- Architectural state ------------------------------------------------
    reg [7:0]  R [0:31];
    reg [7:0]  sreg;
    reg [15:0] pc;
    reg        halt;

    integer k;

    // ---- Instruction fetch (async) -----------------------------------------
    assign pmem_addr_a = pc[PROG_ADDR_W-1:0];
    assign pmem_addr_b = pc[PROG_ADDR_W-1:0] + 1'b1;
    wire [15:0] ir  = pmem_data_a;   // current instruction word
    wire [15:0] ir2 = pmem_data_b;   // following word (immediate/address)

    // ---- Field extraction ---------------------------------------------------
    wire [4:0] d5  = {ir[8], ir[7:4]};        // 5-bit dest reg
    wire [4:0] r5  = {ir[9], ir[3:0]};        // 5-bit src reg
    wire [4:0] di  = {1'b1, ir[7:4]};         // immediate dest reg (R16..R31)
    wire [7:0] K8  = {ir[11:8], ir[3:0]};     // 8-bit immediate
    wire [5:0] io6 = {ir[10:9], ir[3:0]};     // 6-bit I/O address
    wire [2:0] bsel = ir[2:0];                // branch bit select
    wire [15:0] br_off = {{9{ir[9]}}, ir[9:3]};   // signed 7-bit branch offset
    wire [15:0] rj_off = {{4{ir[11]}}, ir[11:0]}; // signed 12-bit rjmp offset

    wire [7:0] Rd  = R[d5];
    wire [7:0] Rr  = R[r5];
    wire [7:0] Rdi = R[di];

    // ---- Combinational decode / datapath -----------------------------------
    reg                    reg_we;
    reg  [4:0]             reg_waddr;
    reg  [7:0]             reg_wdata;
    reg  [7:0]             sreg_n;
    reg  [15:0]            pc_n;
    reg                    halt_n;

    // ALU scratch
    reg  [7:0] a, b, res;
    reg        cin;
    reg  [8:0] add9, sub9;
    reg  [4:0] add4, sub4;
    reg        fC, fZ, fN, fV, fS, fH;

    always @* begin
        // defaults
        reg_we     = 1'b0;
        reg_waddr  = d5;
        reg_wdata  = 8'h00;
        sreg_n     = sreg;
        pc_n       = pc + 16'd1;
        halt_n     = halt;
        dmem_addr  = {DATA_ADDR_W{1'b0}};
        dmem_we    = 1'b0;
        dmem_wdata = 8'h00;
        io_we      = 1'b0;
        io_addr    = 6'h00;
        io_wdata   = 8'h00;

        a = 8'h00; b = 8'h00; cin = 1'b0;
        add9 = 9'h0; sub9 = 9'h0; add4 = 5'h0; sub4 = 5'h0;
        res = 8'h00; fC=0; fZ=0; fN=0; fV=0; fS=0; fH=0;

        casez (ir)
            // ---- control (exact opcodes first) ----
            16'b0000_0000_0000_0000: begin /* NOP */ end
            16'b1001_0100_0111_1000: begin sreg_n[I] = 1'b1; end // SEI
            16'b1001_0100_1111_1000: begin sreg_n[I] = 1'b0; end // CLI
            16'b1001_0101_1000_1000: begin halt_n = 1'b1; pc_n = pc; end // SLEEP

            // ---- ADD / ADC / LSL / ROL ----
            16'b0000_11??_????_????,   // ADD
            16'b0001_11??_????_????: begin // ADC
                a = Rd; b = Rr;
                cin = ir[12] ? sreg[C] : 1'b0; // ir[12]=1 -> ADC
                add9 = {1'b0,a} + {1'b0,b} + cin;
                add4 = {1'b0,a[3:0]} + {1'b0,b[3:0]} + cin;
                res = add9[7:0];
                fC = add9[8]; fH = add4[4];
                fN = res[7];  fZ = (res == 8'h00);
                fV = (~(a[7]^b[7])) & (a[7]^res[7]);
                fS = fN ^ fV;
                reg_we = 1'b1; reg_waddr = d5; reg_wdata = res;
                sreg_n[C]=fC; sreg_n[Z]=fZ; sreg_n[N]=fN;
                sreg_n[V]=fV; sreg_n[S]=fS; sreg_n[H]=fH;
            end

            // ---- SUB / SBC / CP / CPC ----
            // ir[12] : 1 = no carry-in (SUB/CP), 0 = carry-in (SBC/CPC)
            // ir[11] : 1 = write-back (SUB/SBC),  0 = compare only (CP/CPC)
            16'b0001_10??_????_????,   // SUB  0001_10
            16'b0000_10??_????_????,   // SBC  0000_10
            16'b0001_01??_????_????,   // CP   0001_01
            16'b0000_01??_????_????: begin // CPC 0000_01
                a = Rd; b = Rr;
                cin = ir[12] ? 1'b0 : sreg[C];
                sub9 = {1'b0,a} - {1'b0,b} - cin;
                sub4 = {1'b0,a[3:0]} - {1'b0,b[3:0]} - cin;
                res = sub9[7:0];
                fC = sub9[8]; fH = sub4[4];
                fN = res[7];
                fV = (a[7]^b[7]) & (a[7]^res[7]);
                fS = fN ^ fV;
                fZ = ir[12] ? (res == 8'h00) : ((res == 8'h00) & sreg[Z]);
                reg_we    = ir[11];
                reg_waddr = d5;
                reg_wdata = res;
                sreg_n[C]=fC; sreg_n[Z]=fZ; sreg_n[N]=fN;
                sreg_n[V]=fV; sreg_n[S]=fS; sreg_n[H]=fH;
            end

            // ---- AND / EOR / OR / MOV ----
            16'b0010_00??_????_????: begin // AND
                res = Rd & Rr; reg_we=1'b1; reg_waddr=d5; reg_wdata=res;
                sreg_n[V]=1'b0; sreg_n[N]=res[7]; sreg_n[Z]=(res==0); sreg_n[S]=res[7];
            end
            16'b0010_01??_????_????: begin // EOR
                res = Rd ^ Rr; reg_we=1'b1; reg_waddr=d5; reg_wdata=res;
                sreg_n[V]=1'b0; sreg_n[N]=res[7]; sreg_n[Z]=(res==0); sreg_n[S]=res[7];
            end
            16'b0010_10??_????_????: begin // OR
                res = Rd | Rr; reg_we=1'b1; reg_waddr=d5; reg_wdata=res;
                sreg_n[V]=1'b0; sreg_n[N]=res[7]; sreg_n[Z]=(res==0); sreg_n[S]=res[7];
            end
            16'b0010_11??_????_????: begin // MOV
                reg_we=1'b1; reg_waddr=d5; reg_wdata=Rr;
            end

            // ---- immediate ops (R16..R31) ----
            16'b1110_????_????_????: begin // LDI
                reg_we=1'b1; reg_waddr=di; reg_wdata=K8;
            end
            16'b0110_????_????_????: begin // ORI / SBR
                res = Rdi | K8; reg_we=1'b1; reg_waddr=di; reg_wdata=res;
                sreg_n[V]=1'b0; sreg_n[N]=res[7]; sreg_n[Z]=(res==0); sreg_n[S]=res[7];
            end
            16'b0111_????_????_????: begin // ANDI / CBR
                res = Rdi & K8; reg_we=1'b1; reg_waddr=di; reg_wdata=res;
                sreg_n[V]=1'b0; sreg_n[N]=res[7]; sreg_n[Z]=(res==0); sreg_n[S]=res[7];
            end
            16'b0101_????_????_????,   // SUBI
            16'b0011_????_????_????: begin // CPI
                a = Rdi; b = K8;
                sub9 = {1'b0,a} - {1'b0,b};
                sub4 = {1'b0,a[3:0]} - {1'b0,b[3:0]};
                res = sub9[7:0];
                fC=sub9[8]; fH=sub4[4]; fN=res[7]; fZ=(res==0);
                fV=(a[7]^b[7]) & (a[7]^res[7]); fS=fN^fV;
                reg_we = (ir[14:12]==3'b101); // SUBI writes, CPI does not
                reg_waddr = di; reg_wdata = res;
                sreg_n[C]=fC; sreg_n[Z]=fZ; sreg_n[N]=fN;
                sreg_n[V]=fV; sreg_n[S]=fS; sreg_n[H]=fH;
            end

            // ---- unary group 1001_010d_dddd_xxxx ----
            16'b1001_010?_????_0000: begin // COM
                res = ~Rd; reg_we=1'b1; reg_waddr=d5; reg_wdata=res;
                sreg_n[C]=1'b1; sreg_n[V]=1'b0; sreg_n[N]=res[7];
                sreg_n[Z]=(res==0); sreg_n[S]=res[7];
            end
            16'b1001_010?_????_0001: begin // NEG
                res = 8'h00 - Rd; reg_we=1'b1; reg_waddr=d5; reg_wdata=res;
                sreg_n[C]=(res!=8'h00); sreg_n[H]=(res[3]|Rd[3]);
                sreg_n[V]=(res==8'h80); sreg_n[N]=res[7];
                sreg_n[Z]=(res==0); sreg_n[S]=res[7]^(res==8'h80);
            end
            16'b1001_010?_????_0010: begin // SWAP
                res = {Rd[3:0], Rd[7:4]}; reg_we=1'b1; reg_waddr=d5; reg_wdata=res;
            end
            16'b1001_010?_????_0011: begin // INC
                res = Rd + 8'd1; reg_we=1'b1; reg_waddr=d5; reg_wdata=res;
                sreg_n[V]=(Rd==8'h7f); sreg_n[N]=res[7];
                sreg_n[Z]=(res==0); sreg_n[S]=res[7]^(Rd==8'h7f);
            end
            16'b1001_010?_????_1010: begin // DEC
                res = Rd - 8'd1; reg_we=1'b1; reg_waddr=d5; reg_wdata=res;
                sreg_n[V]=(Rd==8'h80); sreg_n[N]=res[7];
                sreg_n[Z]=(res==0); sreg_n[S]=res[7]^(Rd==8'h80);
            end
            16'b1001_010?_????_0110: begin // LSR
                res = {1'b0, Rd[7:1]}; reg_we=1'b1; reg_waddr=d5; reg_wdata=res;
                sreg_n[C]=Rd[0]; sreg_n[N]=1'b0; sreg_n[Z]=(res==0);
                sreg_n[V]=1'b0 ^ Rd[0]; sreg_n[S]=1'b0 ^ (1'b0 ^ Rd[0]);
            end
            16'b1001_010?_????_0101: begin // ASR
                res = {Rd[7], Rd[7:1]}; reg_we=1'b1; reg_waddr=d5; reg_wdata=res;
                sreg_n[C]=Rd[0]; sreg_n[N]=res[7]; sreg_n[Z]=(res==0);
                sreg_n[V]=res[7]^Rd[0]; sreg_n[S]=res[7]^(res[7]^Rd[0]);
            end
            16'b1001_010?_????_0111: begin // ROR
                res = {sreg[C], Rd[7:1]}; reg_we=1'b1; reg_waddr=d5; reg_wdata=res;
                sreg_n[C]=Rd[0]; sreg_n[N]=res[7]; sreg_n[Z]=(res==0);
                sreg_n[V]=res[7]^Rd[0]; sreg_n[S]=res[7]^(res[7]^Rd[0]);
            end

            // ---- data memory (two-word) ----
            16'b1001_000?_????_0000: begin // LDS Rd, k
                dmem_addr = ir2[DATA_ADDR_W-1:0];
                reg_we=1'b1; reg_waddr=d5; reg_wdata=dmem_rdata;
                pc_n = pc + 16'd2;
            end
            16'b1001_001?_????_0000: begin // STS k, Rr
                dmem_addr = ir2[DATA_ADDR_W-1:0];
                dmem_we=1'b1; dmem_wdata=Rd;
                pc_n = pc + 16'd2;
            end

            // ---- I/O ----
            16'b1011_0???_????_????: begin // IN Rd, P
                io_addr = io6;
                reg_we=1'b1; reg_waddr=d5; reg_wdata=io_rdata;
            end
            16'b1011_1???_????_????: begin // OUT P, Rr
                io_we=1'b1; io_addr=io6; io_wdata=Rd;
            end

            // ---- branches ----
            16'b1111_00??_????_????: begin // BRBS b (branch if SREG[b] set)
                if (sreg[bsel]) pc_n = pc + 16'd1 + br_off;
            end
            16'b1111_01??_????_????: begin // BRBC b (branch if SREG[b] clear)
                if (!sreg[bsel]) pc_n = pc + 16'd1 + br_off;
            end

            // ---- relative jump ----
            16'b1100_????_????_????: begin // RJMP
                pc_n = pc + 16'd1 + rj_off;
            end

            default: begin /* unimplemented -> NOP */ end
        endcase
    end

    // ---- Sequential state update -------------------------------------------
    always @(posedge clk or negedge rst_n) begin
        if (!rst_n) begin
            pc   <= 16'h0000;
            sreg <= 8'h00;
            halt <= 1'b0;
            for (k = 0; k < 32; k = k + 1) R[k] <= 8'h00;
        end else if (!halt) begin
            pc   <= pc_n;
            sreg <= sreg_n;
            halt <= halt_n;
            if (reg_we) R[reg_waddr] <= reg_wdata;
        end
    end

    assign halted   = halt;
    assign dbg_data = R[dbg_addr];
    assign dbg_sreg = sreg;
    assign dbg_pc   = pc;

endmodule

src/open8_top.v
// Open8 SoC top: CPU core + program ROM + data SRAM + a single 8-bit I/O port.
// I/O address 0 maps to {port_out (write), port_in (read)}.
module open8_top #(
    parameter PROG_ADDR_W = 12,
    parameter DATA_ADDR_W = 16,
    parameter DMEM_ADDR_W = 12,
    parameter PROG_INIT   = "program.hex"
)(
    input  wire        clk,
    input  wire        rst_n,

    // I/O port
    input  wire [7:0]  port_in,
    output reg  [7:0]  port_out,
    output reg         port_out_we,

    // status + debug
    output wire        halted,
    input  wire [4:0]  dbg_addr,
    output wire [7:0]  dbg_data,
    output wire [7:0]  dbg_sreg,
    output wire [15:0] dbg_pc
);
    // program memory bus
    wire [PROG_ADDR_W-1:0] pa, pb;
    wire [15:0]            da, db;

    // data memory bus
    wire [DATA_ADDR_W-1:0] dmem_addr;
    wire                   dmem_we;
    wire [7:0]             dmem_wdata, dmem_rdata;

    // I/O bus
    wire                   io_we;
    wire [5:0]             io_addr;
    wire [7:0]             io_wdata;
    reg  [7:0]             io_rdata;

    open8_core #(
        .PROG_ADDR_W(PROG_ADDR_W),
        .DATA_ADDR_W(DATA_ADDR_W)
    ) core (
        .clk(clk), .rst_n(rst_n),
        .pmem_addr_a(pa), .pmem_data_a(da),
        .pmem_addr_b(pb), .pmem_data_b(db),
        .dmem_addr(dmem_addr), .dmem_we(dmem_we),
        .dmem_wdata(dmem_wdata), .dmem_rdata(dmem_rdata),
        .io_we(io_we), .io_addr(io_addr), .io_wdata(io_wdata), .io_rdata(io_rdata),
        .halted(halted),
        .dbg_addr(dbg_addr), .dbg_data(dbg_data),
        .dbg_sreg(dbg_sreg), .dbg_pc(dbg_pc)
    );

    open8_pmem #(
        .ADDR_W(PROG_ADDR_W), .INIT(PROG_INIT)
    ) pmem (
        .addr_a(pa), .data_a(da),
        .addr_b(pb), .data_b(db)
    );

    open8_dmem #(
        .ADDR_W(DMEM_ADDR_W), .BUS_W(DATA_ADDR_W)
    ) dmem (
        .clk(clk), .addr(dmem_addr), .we(dmem_we),
        .wdata(dmem_wdata), .rdata(dmem_rdata)
    );

    // I/O read mux
    always @* begin
        io_rdata = 8'h00;
        if (io_addr == 6'd0) io_rdata = port_in;
    end

    // I/O write capture (port 0 -> port_out, with a 1-cycle strobe)
    always @(posedge clk or negedge rst_n) begin
        if (!rst_n) begin
            port_out    <= 8'h00;
            port_out_we <= 1'b0;
        end else begin
            port_out_we <= 1'b0;
            if (io_we && io_addr == 6'd0) begin
                port_out    <= io_wdata;
                port_out_we <= 1'b1;
            end
        end
    end
endmodule

open8.vcd
$version Generated by VerilatedVcd $end
$timescale 1ps $end
 $scope module TOP $end
  $var wire 1 r clk $end
  $var wire 1 s rst_n $end
  $var wire 8 t port_in [7:0] $end
  $var wire 8 u port_out [7:0] $end
  $var wire 1 v port_out_we $end
  $var wire 1 4 halted $end
  $var wire 5 w dbg_addr [4:0] $end
  $var wire 8 x dbg_data [7:0] $end
  $var wire 8 5 dbg_sreg [7:0] $end
  $var wire 16 6 dbg_pc [15:0] $end
  $scope module open8_top $end
   $var wire 32 { PROG_ADDR_W [31:0] $end
   $var wire 32 | DATA_ADDR_W [31:0] $end
   $var wire 32 { DMEM_ADDR_W [31:0] $end
   $var wire 88 } PROG_INIT [87:0] $end
   $var wire 1 r clk $end
   $var wire 1 s rst_n $end
   $var wire 8 t port_in [7:0] $end
   $var wire 8 u port_out [7:0] $end
   $var wire 1 v port_out_we $end
   $var wire 1 4 halted $end
   $var wire 5 w dbg_addr [4:0] $end
   $var wire 8 x dbg_data [7:0] $end
   $var wire 8 5 dbg_sreg [7:0] $end
   $var wire 16 6 dbg_pc [15:0] $end
   $var wire 12 7 pa [11:0] $end
   $var wire 12 8 pb [11:0] $end
   $var wire 16 9 da [15:0] $end
   $var wire 16 : db [15:0] $end
   $var wire 16 ; dmem_addr [15:0] $end
   $var wire 1 < dmem_we $end
   $var wire 8 = dmem_wdata [7:0] $end
   $var wire 8 y dmem_rdata [7:0] $end
   $var wire 1 > io_we $end
   $var wire 6 ? io_addr [5:0] $end
   $var wire 8 @ io_wdata [7:0] $end
   $var wire 8 z io_rdata [7:0] $end
   $scope module core $end
    $var wire 32 { PROG_ADDR_W [31:0] $end
    $var wire 32 | DATA_ADDR_W [31:0] $end
    $var wire 1 r clk $end
    $var wire 1 s rst_n $end
    $var wire 12 7 pmem_addr_a [11:0] $end
    $var wire 16 9 pmem_data_a [15:0] $end
    $var wire 12 8 pmem_addr_b [11:0] $end
    $var wire 16 : pmem_data_b [15:0] $end
    $var wire 16 ; dmem_addr [15:0] $end
    $var wire 1 < dmem_we $end
    $var wire 8 = dmem_wdata [7:0] $end
    $var wire 8 y dmem_rdata [7:0] $end
    $var wire 1 > io_we $end
    $var wire 6 ? io_addr [5:0] $end
    $var wire 8 @ io_wdata [7:0] $end
    $var wire 8 z io_rdata [7:0] $end
    $var wire 1 4 halted $end
    $var wire 5 w dbg_addr [4:0] $end
    $var wire 8 x dbg_data [7:0] $end
    $var wire 8 5 dbg_sreg [7:0] $end
    $var wire 16 6 dbg_pc [15:0] $end
    $var wire 32 "! C [31:0] $end
    $var wire 32 #! Z [31:0] $end
    $var wire 32 $! N [31:0] $end
    $var wire 32 %! V [31:0] $end
    $var wire 32 &! S [31:0] $end
    $var wire 32 '! H [31:0] $end
    $var wire 32 (! T [31:0] $end
    $var wire 32 )! I [31:0] $end
    $var wire 8 A R[0] [7:0] $end
    $var wire 8 B R[1] [7:0] $end
    $var wire 8 C R[2] [7:0] $end
    $var wire 8 D R[3] [7:0] $end
    $var wire 8 E R[4] [7:0] $end
    $var wire 8 F R[5] [7:0] $end
    $var wire 8 G R[6] [7:0] $end
    $var wire 8 H R[7] [7:0] $end
    $var wire 8 I R[8] [7:0] $end
    $var wire 8 J R[9] [7:0] $end
    $var wire 8 K R[10] [7:0] $end
    $var wire 8 L R[11] [7:0] $end
    $var wire 8 M R[12] [7:0] $end
    $var wire 8 N R[13] [7:0] $end
    $var wire 8 O R[14] [7:0] $end
    $var wire 8 P R[15] [7:0] $end
    $var wire 8 Q R[16] [7:0] $end
    $var wire 8 R R[17] [7:0] $end
    $var wire 8 S R[18] [7:0] $end
    $var wire 8 T R[19] [7:0] $end
    $var wire 8 U R[20] [7:0] $end
    $var wire 8 V R[21] [7:0] $end
    $var wire 8 W R[22] [7:0] $end
    $var wire 8 X R[23] [7:0] $end
    $var wire 8 Y R[24] [7:0] $end
    $var wire 8 Z R[25] [7:0] $end
    $var wire 8 [ R[26] [7:0] $end
    $var wire 8 \ R[27] [7:0] $end
    $var wire 8 ] R[28] [7:0] $end
    $var wire 8 ^ R[29] [7:0] $end
    $var wire 8 _ R[30] [7:0] $end
    $var wire 8 ` R[31] [7:0] $end
    $var wire 8 5 sreg [7:0] $end
    $var wire 16 6 pc [15:0] $end
    $var wire 1 4 halt $end
    $var wire 32 a k [31:0] $end
    $var wire 16 9 ir [15:0] $end
    $var wire 16 : ir2 [15:0] $end
    $var wire 5 b d5 [4:0] $end
    $var wire 5 c r5 [4:0] $end
    $var wire 5 d di [4:0] $end
    $var wire 8 e K8 [7:0] $end
    $var wire 6 f io6 [5:0] $end
    $var wire 3 g bsel [2:0] $end
    $var wire 16 h br_off [15:0] $end
    $var wire 16 i rj_off [15:0] $end
    $var wire 8 j Rd [7:0] $end
    $var wire 8 k Rr [7:0] $end
    $var wire 8 l Rdi [7:0] $end
    $var wire 1 m reg_we $end
    $var wire 5 n reg_waddr [4:0] $end
    $var wire 8 $ reg_wdata [7:0] $end
    $var wire 8 % sreg_n [7:0] $end
    $var wire 16 o pc_n [15:0] $end
    $var wire 1 p halt_n $end
    $var wire 8 & a [7:0] $end
    $var wire 8 ' b [7:0] $end
    $var wire 8 ( res [7:0] $end
    $var wire 1 ) cin $end
    $var wire 9 * add9 [8:0] $end
    $var wire 9 + sub9 [8:0] $end
    $var wire 5 , add4 [4:0] $end
    $var wire 5 - sub4 [4:0] $end
    $var wire 1 . fC $end
    $var wire 1 / fZ $end
    $var wire 1 0 fN $end
    $var wire 1 1 fV $end
    $var wire 1 2 fS $end
    $var wire 1 3 fH $end
   $upscope $end
   $scope module dmem $end
    $var wire 32 { ADDR_W [31:0] $end
    $var wire 32 | BUS_W [31:0] $end
    $var wire 1 r clk $end
    $var wire 16 ; addr [15:0] $end
    $var wire 1 < we $end
    $var wire 8 = wdata [7:0] $end
    $var wire 8 y rdata [7:0] $end
    $var wire 32 " i [31:0] $end
    $var wire 12 q a [11:0] $end
   $upscope $end
   $scope module pmem $end
    $var wire 32 { ADDR_W [31:0] $end
    $var wire 88 } INIT [87:0] $end
    $var wire 12 7 addr_a [11:0] $end
    $var wire 16 9 data_a [15:0] $end
    $var wire 12 8 addr_b [11:0] $end
    $var wire 16 : data_b [15:0] $end
    $var wire 32 # i [31:0] $end
   $upscope $end
  $upscope $end
 $upscope $end
$enddefinitions $end


#0
b00000000000000000001000000000000 "
b00000000000000000001000000000000 #
b00000000 $
b00000000 %
b00000000 &
b00000000 '
b00000000 (
0)
b000000000 *
b000000000 +
b00000 ,
b00000 -
0.
0/
00
01
02
03
04
b00000000 5
b0000000000000000 6
b000000000000 7
b000000000001 8
b1110000000000000 9
b1110000000010001 :
b0000000000000000 ;
0<
b00000000 =
0>
b000000 ?
b00000000 @
b00000000 A
b00000000 B
b00000000 C
b00000000 D
b00000000 E
b00000000 F
b00000000 G
b00000000 H
b00000000 I
b00000000 J
b00000000 K
b00000000 L
b00000000 M
b00000000 N
b00000000 O
b00000000 P
b00000000 Q
b00000000 R
b00000000 S
b00000000 T
b00000000 U
b00000000 V
b00000000 W
b00000000 X
b00000000 Y
b00000000 Z
b00000000 [
b00000000 \
b00000000 ]
b00000000 ^
b00000000 _
b00000000 `
b00000000000000000000000000000000 a
b00000 b
b00000 c
b10000 d
b00000000 e
b000000 f
b000 g
b0000000000000000 h
b0000000000000000 i
b00000000 j
b00000000 k
b00000000 l
1m
b10000 n
b0000000000000001 o
0p
b000000000000 q
0r
0s
b00000000 t
b00000000 u
0v
b00000 w
b00000000 x
b00000000 y
b00000000 z
b00000000000000000000000000001100 {
b00000000000000000000000000010000 |
b0111000001110010011011110110011101110010011000010110110100101110011010000110010101111000 }
b00000000000000000000000000000000 "!
b00000000000000000000000000000001 #!
b00000000000000000000000000000010 $!
b00000000000000000000000000000011 %!
b00000000000000000000000000000100 &!
b00000000000000000000000000000101 '!
b00000000000000000000000000000110 (!
b00000000000000000000000000000111 )!
#1
b00000000000000000000000000100000 a
1r
#2
0r
#3
1r
#4
0r
#5
1r
#6
0r
1s
#7
b00000001 $
b0000000000000001 6
b000000000001 7
b000000000010 8
b1110000000010001 9
b1110000000101011 :
b00001 b
b00001 c
b10001 d
b00000001 e
b000001 f
b001 g
b0000000000000010 h
b0000000000010001 i
b10001 n
b0000000000000010 o
1r
#8
0r
#9
b00001011 $
b0000000000000010 6
b000000000010 7
b000000000011 8
b1110000000101011 9
b0000111100000001 :
b00000001 R
b00010 b
b01011 c
b10010 d
b00001011 e
b001011 f
b011 g
b0000000000000101 h
b0000000000101011 i
b10010 n
b0000000000000011 o
1r
#10
0r
#11
b00000001 $
b00000001 '
b00000001 (
b000000001 *
b00001 ,
b0000000000000011 6
b000000000011 7
b000000000100 8
b0000111100000001 9
b1001010100010011 :
b00001011 S
b10000 b
b10001 c
b10000 d
b11110001 e
b110001 f
b001 g
b1111111111100000 h
b1111111100000001 i
b00000001 k
b10000 n
b0000000000000100 o
1r
#12
0r
#13
b00000010 $
b00000000 '
b00000010 (
b000000000 *
b00000 ,
b0000000000000100 6
b000000000100 7
b000000000101 8
b1001010100010011 9
b0001011100010010 :
b00000001 Q
b10001 b
b00011 c
b10001 d
b01010011 e
b100011 f
b011 g
b0000000000100010 h
b0000010100010011 i
b00000001 j
b00000000 k
b00000001 l
b10001 n
b0000000000000101 o
1r
#14
0r
#15
b11110111 $
b00110101 %
b00000010 &
b00001011 '
b11110111 (
b111110111 +
b10111 -
1.
10
12
13
b0000000000000101 6
b000000000101 7
b000000000110 8
b0001011100010010 9
b1111011111100001 :
b00000010 R
b10010 c
b01110010 e
b110010 f
b010 g
b1111111111100010 h
b0000011100010010 i
b00000010 j
b00001011 k
b00000010 l
0m
b0000000000000110 o
1r
#16
0r
#17
b00000000 $
b00000000 &
b00000000 '
b00000000 (
b000000000 +
b00000 -
0.
00
02
03
b00110101 5
b0000000000000110 6
b000000000110 7
b000000000111 8
b1111011111100001 9
b1011100100000000 :
b11110 b
b10001 c
b11110 d
b01110001 e
b110001 f
b001 g
b1111111111111100 h
b0000011111100001 i
b00000000 j
b00000010 k
b00000000 l
b11110 n
b0000000000000011 o
1r
#18
0r
#19
b00000011 $
b00000000 %
b00000001 &
b00000010 '
b00000011 (
b000000011 *
b00011 ,
b0000000000000011 6
b000000000011 7
b000000000100 8
b0000111100000001 9
b1001010100010011 :
b10000 b
b10000 d
b11110001 e
b1111111111100000 h
b1111111100000001 i
b00000001 j
b00000001 l
1m
b10000 n
b0000000000000100 o
1r
#20
0r
#21
b00000000 &
b00000000 '
b000000000 *
b00000 ,
b00000000 5
b0000000000000100 6
b000000000100 7
b000000000101 8
b1001010100010011 9
b0001011100010010 :
b00000011 Q
b10001 b
b00011 c
b10001 d
b01010011 e
b100011 f
b011 g
b0000000000100010 h
b0000010100010011 i
b00000010 j
b00000000 k
b00000010 l
b10001 n
b0000000000000101 o
1r
#22
0r
#23
b11111000 $
b00110101 %
b00000011 &
b00001011 '
b11111000 (
b111111000 +
b11000 -
1.
10
12
13
b0000000000000101 6
b000000000101 7
b000000000110 8
b0001011100010010 9
b1111011111100001 :
b00000011 R
b10010 c
b01110010 e
b110010 f
b010 g
b1111111111100010 h
b0000011100010010 i
b00000011 j
b00001011 k
b00000011 l
0m
b0000000000000110 o
1r
#24
0r
#25
b00000000 $
b00000000 &
b00000000 '
b00000000 (
b000000000 +
b00000 -
0.
00
02
03
b00110101 5
b0000000000000110 6
b000000000110 7
b000000000111 8
b1111011111100001 9
b1011100100000000 :
b11110 b
b10001 c
b11110 d
b01110001 e
b110001 f
b001 g
b1111111111111100 h
b0000011111100001 i
b00000000 j
b00000011 k
b00000000 l
b11110 n
b0000000000000011 o
1r
#26
0r
#27
b00000110 $
b00000000 %
b00000011 &
b00000011 '
b00000110 (
b000000110 *
b00110 ,
b0000000000000011 6
b000000000011 7
b000000000100 8
b0000111100000001 9
b1001010100010011 :
b10000 b
b10000 d
b11110001 e
b1111111111100000 h
b1111111100000001 i
b00000011 j
b00000011 l
1m
b10000 n
b0000000000000100 o
1r
#28
0r
#29
b00000100 $
b00000000 &
b00000000 '
b00000100 (
b000000000 *
b00000 ,
b00000000 5
b0000000000000100 6
b000000000100 7
b000000000101 8
b1001010100010011 9
b0001011100010010 :
b00000110 Q
b10001 b
b00011 c
b10001 d
b01010011 e
b100011 f
b011 g
b0000000000100010 h
b0000010100010011 i
b00000000 k
b10001 n
b0000000000000101 o
1r
#30
0r
#31
b11111001 $
b00110101 %
b00000100 &
b00001011 '
b11111001 (
b111111001 +
b11001 -
1.
10
12
13
b0000000000000101 6
b000000000101 7
b000000000110 8
b0001011100010010 9
b1111011111100001 :
b00000100 R
b10010 c
b01110010 e
b110010 f
b010 g
b1111111111100010 h
b0000011100010010 i
b00000100 j
b00001011 k
b00000100 l
0m
b0000000000000110 o
1r
#32
0r
